{"py/object": "rasa.core.featurizers.tracker_featurizers.MaxHistoryTrackerFeaturizer", "state_featurizer": {"py/object": "rasa.core.featurizers.single_state_featurizer.SingleStateFeaturizer", "_default_feature_states": {"intent": {"ask_art_facts": 0, "ask_art_ten_facts": 1, "ask_beuys_facts": 2, "ask_beuys_ten_facts": 3, "ask_fluxus": 4, "ask_knowing_beuys": 5, "ask_performances": 6, "ask_social_sculpture": 7, "ask_understanding_art": 8, "back": 9, "nlu_fallback": 10, "out_of_scope": 11, "restart": 12, "session_start": 13}, "action_name": {"action_listen": 0, "action_restart": 1, "action_session_start": 2, "action_default_fallback": 3, "action_deactivate_loop": 4, "action_revert_fallback_events": 5, "action_default_ask_affirmation": 6, "action_default_ask_rephrase": 7, "action_two_stage_fallback": 8, "action_unlikely_intent": 9, "action_back": 10, "action_send_text": 11, "...": 12, "action_extract_slots": 13, "action_cancel_flow": 14, "action_correct_flow_slot": 15, "action_clarify_flows": 16, "action_run_slot_rejections": 17, "action_clean_stack": 18, "action_trigger_search": 19, "action_trigger_chitchat": 20, "action_reset_routing": 21, "utter_social_sculpture": 22, "utter_fluxus": 23, "utter_performances": 24, "utter_knowing_beuys": 25, "utter_understanding_art": 26, "utter_beuys_facts": 27, "utter_art_facts": 28, "utter_beuys_ten_facts": 29, "utter_art_ten_facts": 30}, "entities": {}, "slots": {}, "active_loop": {}}, "action_texts": [], "entity_tag_specs": []}, "max_history": 5, "remove_duplicates": true}